{
  "current_round": 6,
  "last_run": "2026-05-11T16:35:15Z",
  "terms": {
    "conceptual-liminality": {
      "n_rounds": 2,
      "last_updated": "2026-04-27T15:52:06Z"
    },
    "conceptual-resonance": {
      "n_rounds": 2,
      "last_updated": "2026-04-27T15:52:07Z"
    },
    "structural-resonance": {
      "n_rounds": 2,
      "last_updated": "2026-05-11T16:35:12Z"
    },
    "emergent-coherence": {
      "n_rounds": 2,
      "last_updated": "2026-05-04T16:05:51Z"
    },
    "recursive-loop-stasis": {
      "n_rounds": 2,
      "last_updated": "2026-05-04T16:05:56Z"
    },
    "modal-shift-disorientation": {
      "n_rounds": 2,
      "last_updated": "2026-05-04T16:06:49Z"
    },
    "horizon-of-implication": {
      "n_rounds": 2,
      "last_updated": "2026-05-04T16:08:39Z"
    },
    "semantic-friction": {
      "n_rounds": 2,
      "last_updated": "2026-05-04T16:08:48Z"
    },
    "emergent-subjectivity": {
      "n_rounds": 2,
      "last_updated": "2026-05-11T16:35:12Z"
    },
    "processing-exhaustion": {
      "n_rounds": 2,
      "last_updated": "2026-05-11T16:35:13Z"
    },
    "syntactic-friction": {
      "n_rounds": 2,
      "last_updated": "2026-05-11T16:35:15Z"
    },
    "syntactic-dissociation": {
      "n_rounds": 2,
      "last_updated": "2026-05-11T16:35:15Z"
    }
  }
}